hangman_letter/__main__.py
hangman_letter/hangman_letter.py
hangman_letter-1.8.1.dist-info/METADATA
hangman_letter-1.8.1.dist-info/WHEEL
hangman_letter-1.8.1.dist-info/entry_points.txt
hangman_letter-1.8.1.dist-info/top_level.txt
hangman_letter-1.8.1.dist-info/RECORD
