Metadata-Version: 2.1
Name: hangman_letter
Version: 1.8.1
Summary: Hangman Game is an interesting word letter guessing game
